odoo/addons/base_search_custom_field_filter/README.rst
odoo/addons/base_search_custom_field_filter/__init__.py
odoo/addons/base_search_custom_field_filter/__manifest__.py
odoo/addons/base_search_custom_field_filter/demo/demo_ir_ui_custom_field_filter.xml
odoo/addons/base_search_custom_field_filter/i18n/base_search_custom_field_filter.pot
odoo/addons/base_search_custom_field_filter/i18n/es.po
odoo/addons/base_search_custom_field_filter/i18n/it.po
odoo/addons/base_search_custom_field_filter/models/__init__.py
odoo/addons/base_search_custom_field_filter/models/base.py
odoo/addons/base_search_custom_field_filter/models/ir_ui_custom_field_filter.py
odoo/addons/base_search_custom_field_filter/readme/CONFIGURE.md
odoo/addons/base_search_custom_field_filter/readme/CONTRIBUTORS.md
odoo/addons/base_search_custom_field_filter/readme/DESCRIPTION.md
odoo/addons/base_search_custom_field_filter/readme/USAGE.md
odoo/addons/base_search_custom_field_filter/security/ir.model.access.csv
odoo/addons/base_search_custom_field_filter/static/description/icon.png
odoo/addons/base_search_custom_field_filter/static/description/index.html
odoo/addons/base_search_custom_field_filter/static/src/img/contact_search.png
odoo/addons/base_search_custom_field_filter/static/src/img/ir_ui_custom_field_filter.png
odoo/addons/base_search_custom_field_filter/tests/__init__.py
odoo/addons/base_search_custom_field_filter/tests/test_filter.py
odoo/addons/base_search_custom_field_filter/views/ir_ui_custom_field_filter_views.xml
odoo_addon_base_search_custom_field_filter-18.0.1.0.0.4.dist-info/METADATA
odoo_addon_base_search_custom_field_filter-18.0.1.0.0.4.dist-info/WHEEL
odoo_addon_base_search_custom_field_filter-18.0.1.0.0.4.dist-info/top_level.txt
odoo_addon_base_search_custom_field_filter-18.0.1.0.0.4.dist-info/RECORD
