Metadata-Version: 2.1
Name: odoo-addon-base_search_custom_field_filter
Version: 18.0.1.0.0.4
Requires-Python: >=3.10
Requires-Dist: odoo==18.0.*
Summary: Add custom filters for fields via UI
Home-page: https://github.com/OCA/server-ux
License: AGPL-3
Author: Tecnativa, Amitaujas, Odoo Community Association (OCA)
Author-email: support@odoo-community.org
Classifier: Programming Language :: Python
Classifier: Framework :: Odoo
Classifier: Framework :: Odoo :: 18.0
Classifier: License :: OSI Approved :: GNU Affero General Public License v3
